wtforms_piccolo/__init__.py
wtforms_piccolo/orm.py
wtforms_piccolo-0.2.1.dist-info/LICENSE
wtforms_piccolo-0.2.1.dist-info/METADATA
wtforms_piccolo-0.2.1.dist-info/WHEEL
wtforms_piccolo-0.2.1.dist-info/top_level.txt
wtforms_piccolo-0.2.1.dist-info/RECORD
