Metadata-Version: 2.1
Name: wtforms-piccolo
Version: 0.2.1
Summary: Form generation utilities for Piccolo ORM Table class
Home-page: https://github.com/sinisaos/wtforms-piccolo
Author: sinisaos
Author-email: sinisaos@gmail.com
License: MIT
Platform: UNKNOWN
Classifier: License :: OSI Approved :: MIT License
Classifier: Programming Language :: Python
Classifier: Programming Language :: Python :: 3
Classifier: Programming Language :: Python :: 3.7
Classifier: Programming Language :: Python :: 3.8
Classifier: Programming Language :: Python :: 3.9
Classifier: Programming Language :: Python :: 3.10
Classifier: Programming Language :: Python :: Implementation :: CPython
Requires-Python: >=3.7
License-File: LICENSE
Requires-Dist: piccolo
Requires-Dist: wtforms
Requires-Dist: wtforms[email]
